CmakeCookbookZhongwenbanFix1/README.md
CmakeCookbookZhongwenbanFix1/__init__.py
CmakeCookbookZhongwenbanFix1/__main__.py
CmakeCookbookZhongwenbanFix1/file.epub
CmakeCookbookZhongwenbanFix1/index.html
CmakeCookbookZhongwenbanFix1/css/__init__.py
CmakeCookbookZhongwenbanFix1/css/annotations.css
CmakeCookbookZhongwenbanFix1/css/main.css
CmakeCookbookZhongwenbanFix1/css/normalize.css
CmakeCookbookZhongwenbanFix1/css/popup.css
CmakeCookbookZhongwenbanFix1/font/__init__.py
CmakeCookbookZhongwenbanFix1/font/fontello.eot
CmakeCookbookZhongwenbanFix1/font/fontello.svg
CmakeCookbookZhongwenbanFix1/font/fontello.ttf
CmakeCookbookZhongwenbanFix1/font/fontello.woff
CmakeCookbookZhongwenbanFix1/img/__init__.py
CmakeCookbookZhongwenbanFix1/img/annotator-glyph-sprite.png
CmakeCookbookZhongwenbanFix1/img/annotator-icon-sprite.png
CmakeCookbookZhongwenbanFix1/img/apple-touch-icon.png
CmakeCookbookZhongwenbanFix1/img/cancelfullscreen.png
CmakeCookbookZhongwenbanFix1/img/close.png
CmakeCookbookZhongwenbanFix1/img/fullscreen.png
CmakeCookbookZhongwenbanFix1/img/loader.gif
CmakeCookbookZhongwenbanFix1/img/menu-icon.png
CmakeCookbookZhongwenbanFix1/img/save.png
CmakeCookbookZhongwenbanFix1/img/saved.png
CmakeCookbookZhongwenbanFix1/img/settings-s.png
CmakeCookbookZhongwenbanFix1/img/settings.png
CmakeCookbookZhongwenbanFix1/img/star.png
CmakeCookbookZhongwenbanFix1/js/__init__.py
CmakeCookbookZhongwenbanFix1/js/epub.js
CmakeCookbookZhongwenbanFix1/js/epub.min.js
CmakeCookbookZhongwenbanFix1/js/epub.min.map
CmakeCookbookZhongwenbanFix1/js/hooks.min.js
CmakeCookbookZhongwenbanFix1/js/hooks.min.map
CmakeCookbookZhongwenbanFix1/js/reader.js
CmakeCookbookZhongwenbanFix1/js/reader.js.map
CmakeCookbookZhongwenbanFix1/js/reader.min.js
CmakeCookbookZhongwenbanFix1/js/reader.min.map
CmakeCookbookZhongwenbanFix1/js/hooks/__init__.py
CmakeCookbookZhongwenbanFix1/js/hooks/extensions/__init__.py
CmakeCookbookZhongwenbanFix1/js/hooks/extensions/highlight.js
cmake_cookbook_zhongwenban_fix1-2025.3.24.0.dist-info/METADATA
cmake_cookbook_zhongwenban_fix1-2025.3.24.0.dist-info/WHEEL
cmake_cookbook_zhongwenban_fix1-2025.3.24.0.dist-info/entry_points.txt
cmake_cookbook_zhongwenban_fix1-2025.3.24.0.dist-info/top_level.txt
cmake_cookbook_zhongwenban_fix1-2025.3.24.0.dist-info/RECORD
